setup.py
udacity_dsnd_1_probability/Binomialdistribution.py
udacity_dsnd_1_probability/Gaussiandistribution.py
udacity_dsnd_1_probability/Generaldistribution.py
udacity_dsnd_1_probability/__init__.py
udacity_dsnd_1_probability/test.py
udacity_dsnd_1_probability.egg-info/PKG-INFO
udacity_dsnd_1_probability.egg-info/SOURCES.txt
udacity_dsnd_1_probability.egg-info/dependency_links.txt
udacity_dsnd_1_probability.egg-info/not-zip-safe
udacity_dsnd_1_probability.egg-info/top_level.txt