Metadata-Version: 2.1
Name: udacity-dsnd-1-probability
Version: 0.1
Summary: Gaussian and Binomial distributions
